LICENSE.txt
MANIFEST.in
README.md
setup.cfg
setup.py
mustard/__init__.py
mustard/__main__.py
mustard/mustard
mustard/mustard.kv
mustard/mustard_gui.py
mustard/viewer.py
mustard/graphics/IIT-EDR-logo-t1.png
mustard/graphics/flip_horiz.png
mustard/graphics/flip_horiz_off.png
mustard/graphics/flip_vert.png
mustard/graphics/flip_vert_off.png
mustard/graphics/play_pause.png
mustard/graphics/play_pause_off.png
mustard/graphics/slide.png
mustard/graphics/slide_back.png
mustard/graphics/slide_back_off.png
mustard/graphics/slide_off.png
mustard/graphics/step.png
mustard/graphics/step_back.png
mustard/graphics/step_back_off.png
mustard/graphics/step_off.png
mustard/graphics/stop.png
mustard/graphics/stop_off.png
mustard_gui.egg-info/PKG-INFO
mustard_gui.egg-info/SOURCES.txt
mustard_gui.egg-info/dependency_links.txt
mustard_gui.egg-info/requires.txt
mustard_gui.egg-info/top_level.txt